lint_test/__init__.py
lint_test/how_long.py
lint_test-0.1.0.dist-info/WHEEL
lint_test-0.1.0.dist-info/METADATA
lint_test-0.1.0.dist-info/RECORD
